jsontas/__init__.py
jsontas/__main__.py
jsontas/dataset.py
jsontas/jsontas.py
jsontas/data_structures/__init__.py
jsontas/data_structures/condition.py
jsontas/data_structures/datastructure.py
jsontas/data_structures/expand.py
jsontas/data_structures/filter.py
jsontas/data_structures/from_item.py
jsontas/data_structures/list.py
jsontas/data_structures/operator.py
jsontas/data_structures/reduce.py
jsontas/data_structures/request.py
jsontas/data_structures/wait.py
jsontas-1.4.2.dist-info/licenses/AUTHORS.rst
jsontas-1.4.2.dist-info/licenses/LICENSE.txt
jsontas-1.4.2.dist-info/METADATA
jsontas-1.4.2.dist-info/WHEEL
jsontas-1.4.2.dist-info/entry_points.txt
jsontas-1.4.2.dist-info/top_level.txt
jsontas-1.4.2.dist-info/RECORD
