Metadata-Version: 2.4
Name: jsontas
Version: 1.4.2
Summary: JSONTas is a tool for generating dynamic JSON structures.
Author-email: Tobias Persson <tobias.persson@axis.com>
License-Expression: Apache-2.0
Project-URL: Homepage, https://github.com/AxisCommunications/jsontas/
Project-URL: Documentation, https://jsontas.readthedocs.io/
Classifier: Development Status :: 4 - Beta
Classifier: Programming Language :: Python
Classifier: Programming Language :: Python :: 3
Classifier: Programming Language :: Python :: 3.9
Requires-Python: >=3.9
License-File: LICENSE.txt
License-File: AUTHORS.rst
Requires-Dist: requests
Provides-Extra: testing
Requires-Dist: pytest; extra == "testing"
Requires-Dist: pytest-cov; extra == "testing"
Dynamic: license-file
